YCPython/Hello.py
YCPython/YCClass.py
YCPython/YCClass1.py
YCPython/YCFunction.py
YCPython/YCFunction1.py
YCPython/YCHello.py
YCPython/__init__.py
YCPython-0.0.1.6.dist-info/METADATA
YCPython-0.0.1.6.dist-info/WHEEL
YCPython-0.0.1.6.dist-info/top_level.txt
YCPython-0.0.1.6.dist-info/RECORD
