Metadata-Version: 2.1
Name: YCPython
Version: 0.0.1.6
Summary: Python package by YuChulYANG
Home-page: https://gitlab.com/ycyang/YCPython/
Author: YuChul YANG
Author-email: yangyuchul@gmail.com
License: UNKNOWN
Platform: UNKNOWN
